pyfsense_client/__init__.py
pyfsense_client/v1/__init__.py
pyfsense_client/v1/client/__init__.py
pyfsense_client/v1/client/abc.py
pyfsense_client/v1/client/client.py
pyfsense_client/v1/client/types.py
pyfsense_client/v1/mixins/__init__.py
pyfsense_client/v1/mixins/dns.py
pyfsense_client/v1/mixins/firewall.py
pyfsense_client/v1/mixins/firewall_alias.py
pyfsense_client/v1/mixins/interface.py
pyfsense_client/v1/mixins/routing.py
pyfsense_client/v1/mixins/service.py
pyfsense_client/v1/mixins/status.py
pyfsense_client/v1/mixins/system.py
pyfsense_client/v1/mixins/user.py
pyfsense_client/v1/models/__init__.py
pyfsense_client/v1/models/firewall_alias.py
pyfsense_client/v2/__init__.py
pyfsense_client/v2/client.py
pyfsense_client/v2/exceptions.py
pyfsense_client/v2/models/__init__.py
pyfsense_client/v2/models/client.py
pyfsense_client/v2/models/dhcp.py
pyfsense_client/v2/models/firewall_alias.py
pyfsense_client-0.5.0.dist-info/METADATA
pyfsense_client-0.5.0.dist-info/WHEEL
pyfsense_client-0.5.0.dist-info/licenses/LICENSE
pyfsense_client-0.5.0.dist-info/RECORD
