Metadata-Version: 2.4
Name: pyfsense-client
Version: 0.5.0
Summary: A client for the unofficial pfSense API.
Project-URL: homepage, https://github.com/devinbarry/pyfsense-client
Project-URL: repository, https://github.com/devinbarry/pyfsense-client
Project-URL: documentation, https://yaleman.github.io/pfsense-api-client/
Author-email: Devin Barry <devinbarry@users.noreply.github.com>, James Hodgkinson <james@terminaloutcomes.com>
License:                     GNU AFFERO GENERAL PUBLIC LICENSE
License-File: LICENSE
Keywords: API,pfsense
Classifier: Development Status :: 4 - Beta
Classifier: Intended Audience :: Developers
Classifier: Programming Language :: Python :: 3
Classifier: Programming Language :: Python :: 3.11
Classifier: Programming Language :: Python :: 3.12
Classifier: Programming Language :: Python :: 3.13
Classifier: Topic :: Software Development :: Libraries :: Python Modules
Requires-Python: >=3.11
Requires-Dist: pydantic>=2.10
Requires-Dist: requests
Provides-Extra: dev
Requires-Dist: pytest; extra == 'dev'
Requires-Dist: python-dotenv; extra == 'dev'
Requires-Dist: ruff; extra == 'dev'
